{
    "wallpaper": "/home/municorn/.config/wpg/wallpapers/Coast.jpg",
    "alpha": "100",

    "special": {
        "background": "#0f1317",
        "foreground": "#eaffff",
        "cursor": "#eaffff"
    },
    "colors": {
        "color0": "#0f1317",
        "color1": "#9ABDDE",
        "color2": "#6B92B1",
        "color3": "#91B4D2",
        "color4": "#637B91",
        "color5": "#88A2B8",
        "color6": "#789FC3",
        "color7": "#c5d8e7",
        "color8": "#222b35",
        "color9": "#aff6ff",
        "color10": "#78bff8",
        "color11": "#a5ebff",
        "color12": "#70a0cc",
        "color13": "#9cd4ff",
        "color14": "#87cfff",
        "color15": "#eaffff"
    }
}
