{
    "wallpaper": "/home/municorn/.config/wpg/wallpapers/Coaster.jpg",
    "alpha": "100",

    "special": {
        "background": "#0C0D05",
        "foreground": "#fbffff",
        "cursor": "#fbffff"
    },
    "colors": {
        "color0": "#0C0D05",
        "color1": "#827E7F",
        "color2": "#A19F9F",
        "color3": "#AB9462",
        "color4": "#60708E",
        "color5": "#A0B0D2",
        "color6": "#7690B7",
        "color7": "#d8ddde",
        "color8": "#2e3211",
        "color9": "#b9939c",
        "color10": "#e6b9b9",
        "color11": "#efc66d",
        "color12": "#6d8cc8",
        "color13": "#b8dcff",
        "color14": "#85b7ff",
        "color15": "#fbffff"
    }
}
